PgEngine/__init__.py
PgEngine-0.1.dist-info/METADATA
PgEngine-0.1.dist-info/RECORD
PgEngine-0.1.dist-info/WHEEL
PgEngine-0.1.dist-info/top_level.txt
