Metadata-Version: 2.1
Name: PgEngine
Version: 0.1
Summary: Postgres Python Engine
Home-page: UNKNOWN
Author: Prabir Ghosh
Author-email: mymail.prabir@gmail.com
License: MIT
Platform: UNKNOWN
Requires-Dist: pandas
Requires-Dist: sqlalchemy
